{"ticker": "HBAN", "quarters": [{"date": "2026-04-23", "time": "08:00", "eps_actual": null, "eps_estimate": 0.35, "eps_surprise_pct": null, "revenue": null, "revenue_yoy": null}, {"date": "2026-01-22", "time": "06:00", "eps_actual": 0.37, "eps_estimate": 0.38, "eps_surprise_pct": -1.34, "revenue": 2139000000, "revenue_yoy": 9.5}, {"date": "2025-10-17", "time": "07:00", "eps_actual": 0.41, "eps_estimate": 0.38, "eps_surprise_pct": 9.05, "revenue": 2134000000, "revenue_yoy": null}, {"date": "2025-07-18", "time": "07:00", "eps_actual": 0.35, "eps_estimate": 0.35, "eps_surprise_pct": 1.16, "revenue": 1938000000, "revenue_yoy": null}, {"date": "2025-04-17", "time": "07:00", "eps_actual": 0.34, "eps_estimate": 0.31, "eps_surprise_pct": 9.11, "revenue": 1920000000, "revenue_yoy": null}, {"date": "2025-01-17", "time": "07:00", "eps_actual": 0.33, "eps_estimate": 0.32, "eps_surprise_pct": 5.99, "revenue": 1954000000, "revenue_yoy": null}, {"date": "2024-10-17", "time": "07:00", "eps_actual": 0.33, "eps_estimate": 0.3, "eps_surprise_pct": 10.36, "revenue": null, "revenue_yoy": null}, {"date": "2024-07-19", "time": "06:00", "eps_actual": 0.3, "eps_estimate": 0.28, "eps_surprise_pct": 6.57, "revenue": null, "revenue_yoy": null}, {"date": "2024-04-19", "time": "06:00", "eps_actual": 0.26, "eps_estimate": 0.24, "eps_surprise_pct": 8.02, "revenue": null, "revenue_yoy": null}, {"date": "2024-01-19", "time": "06:00", "eps_actual": 0.15, "eps_estimate": 0.17, "eps_surprise_pct": -9.89, "revenue": null, "revenue_yoy": null}, {"date": "2023-10-20", "time": "07:00", "eps_actual": 0.36, "eps_estimate": 0.32, "eps_surprise_pct": 11.55, "revenue": null, "revenue_yoy": null}, {"date": "2023-07-21", "time": "07:00", "eps_actual": 0.35, "eps_estimate": 0.33, "eps_surprise_pct": 5.31, "revenue": null, "revenue_yoy": null}]}